{
    "serverTime": 1727362367,
    "meta": {
        "movies": [
            {
                "id": "OAV34I",
                "frmtId": "TtdX_wUyN",
                "name": "Devara - Part 1",
                "imgPath": "https://assetscdn1.paytm.com/images/cinema/Devara---Part-1--705x750-ff23a0e0-ccc6-11ee-a6f3-b9b401515283.jpg",
                "appImgPath": "https://assetscdn1.paytm.com/images/cinema/Devara-608x800-87e29260-7834-11ef-ad27-dfa11df60ee4.jpg",
                "cvrPath": "https://assetscdn1.paytm.com/images/cinema/we-a407a150-7b23-11ef-84df-ff7d1a67840c.jpg",
                "appCvrPath": "https://assetscdn1.paytm.com/images/cinema/App-cover-a62c7d20-7b23-11ef-8892-f397183e5623.jpg",
                "thumbnail": null,
                "edgeBanner": "https://assetscdn1.paytm.com/images/cinema/Devara---Part-1--1035%E2%80%8A%C3%97%E2%80%8A420-118bd900-ccc7-11ee-a6f3-b9b401515283.jpg",
                "trailer": "https://youtu.be/5cx7rvMvAWo",
                "censor": "U/A",
                "duration": 178,
                "grn": [
                    "Action",
                    "Drama",
                    "Thriller"
                ],
                "scrnFmt": "2D",
                "sndFmt": "none",
                "rnr": {
                    "hasUReview": 0,
                    "hasContent": 1
                },
                "isNew": false,
                "imxImgUrl": null,
                "contentId": 159964,
                "label": "Devara - Part 1",
                "lang": "Telugu"
            }
        ],
        "filterBuckets": {
            "timeBuckets": [
                {
                    "sTime": "05:00",
                    "eTime": "11:59",
                    "desc": "5:00 AM to 11:59 AM",
                    "dText": "Morning",
                    "desc1": "Till 12 PM"
                },
                {
                    "sTime": "12:00",
                    "eTime": "15:59",
                    "desc": "12:00 PM to 3:59 PM",
                    "dText": "Afternoon",
                    "desc1": "Till 4 PM"
                },
                {
                    "sTime": "16:00",
                    "eTime": "18:59",
                    "desc": "4:00 PM to 6:59 PM",
                    "dText": "Evening",
                    "desc1": "Till 7 PM"
                },
                {
                    "sTime": "19:00",
                    "eTime": "04:59",
                    "desc": "7:00 PM to 4:59 AM",
                    "dText": "Night",
                    "desc1": "After 7 PM"
                }
            ],
            "priceBuckets": [
                {
                    "min": "0",
                    "max": "99",
                    "desc": "Below Rs 100"
                },
                {
                    "min": "100",
                    "max": "199",
                    "desc": "Rs 100 - Rs 199"
                },
                {
                    "min": "200",
                    "max": "299",
                    "desc": "Rs 200 - Rs 299"
                },
                {
                    "min": "300",
                    "max": "399",
                    "desc": "Rs 300 - Rs 399"
                },
                {
                    "min": "400",
                    "max": "NA",
                    "desc": "Rs 400 or above"
                }
            ],
            "showTimeBuckets": [
                {
                    "sTime": "00:00",
                    "eTime": "08:00",
                    "desc": "12 AM to 8 AM",
                    "dText": "Early Morning",
                    "desc1": "Till 8 AM"
                },
                {
                    "sTime": "08:00",
                    "eTime": "12:00",
                    "desc": "8 AM to 12 PM",
                    "dText": "Morning",
                    "desc1": "Till 12 PM"
                },
                {
                    "sTime": "12:00",
                    "eTime": "16:00",
                    "desc": "12 PM to 4 PM",
                    "dText": "Afternoon",
                    "desc1": "Till 4 PM"
                },
                {
                    "sTime": "16:00",
                    "eTime": "19:00",
                    "desc": "4 PM to 7 PM",
                    "dText": "Evening",
                    "desc1": "Till 7 PM"
                },
                {
                    "sTime": "19:00",
                    "eTime": "23:59",
                    "desc": "7 PM to 12 AM",
                    "dText": "Night",
                    "desc1": "Till 12 AM"
                }
            ]
        },
        "amenities": [
            {
                "id": 2,
                "name": "Parking",
                "rank": 1
            },
            {
                "id": 1,
                "name": "Mobile Ticket",
                "rank": 2
            },
            {
                "id": 3,
                "name": "Online Food",
                "rank": 3
            },
            {
                "id": 5,
                "name": "Recliners",
                "rank": 4
            },
            {
                "id": 6,
                "name": "Paytm Accepted",
                "rank": 5
            },
            {
                "id": 4,
                "name": "Wheelchair Friendly",
                "rank": 6
            },
            {
                "id": 7,
                "name": "RGB Laser",
                "rank": 7
            },
            {
                "id": 8,
                "name": "Dolby Atmos",
                "rank": 8
            },
            {
                "id": 9,
                "name": "IMAX",
                "rank": 9
            },
            {
                "id": 10,
                "name": "4K",
                "rank": 10
            },
            {
                "id": 11,
                "name": "AC",
                "rank": 11
            },
            {
                "id": 12,
                "name": "WIFI",
                "rank": 12
            },
            {
                "id": 13,
                "name": "Food Court",
                "rank": 13
            },
            {
                "id": 14,
                "name": "Gaming Zone",
                "rank": 14
            },
            {
                "id": 15,
                "name": "2K",
                "rank": 15
            },
            {
                "id": 16,
                "name": "4D",
                "rank": 16
            },
            {
                "id": 17,
                "name": "4DX",
                "rank": 17
            },
            {
                "id": 18,
                "name": "Dolby 7.1",
                "rank": 18
            },
            {
                "id": 19,
                "name": "Air conditioning",
                "rank": 19
            },
            {
                "id": 20,
                "name": "Metro Train",
                "rank": 20
            },
            {
                "id": 21,
                "name": "Sofa",
                "rank": 21
            },
            {
                "id": 22,
                "name": "Social Seating",
                "rank": 22
            },
            {
                "id": 23,
                "name": "Wheelchair Assistance",
                "rank": 23
            },
            {
                "id": 24,
                "name": "Silver Screen",
                "rank": 24
            },
            {
                "id": 25,
                "name": "Food & Beverages",
                "rank": 25
            },
            {
                "id": 26,
                "name": "Paper Less Ticketing",
                "rank": 26
            },
            {
                "id": 27,
                "name": "Handicapped Washroom",
                "rank": 27
            },
            {
                "id": 28,
                "name": "Free Parking",
                "rank": 28
            },
            {
                "id": 29,
                "name": "Baggage Counter",
                "rank": 29
            },
            {
                "id": 30,
                "name": "Dolby 4 Way 11.1",
                "rank": 30
            },
            {
                "id": 31,
                "name": "Barco 4K Ultra HD",
                "rank": 31
            }
        ],
        "cinemas": [
            {
                "id": 1024431,
                "pid": 1707,
                "name": "PVR INOX Sunny Trade Center, Jaipur",
                "address": "Sunny Trade Center, 3rd Floor, New Aatish Market, Mansarovar, Jaipur, Rajasthan 302020, India",
                "pincode": "302020",
                "lat": 26.87665,
                "lon": 75.761107,
                "cityId": 13,
                "appCovrImgUrl": "",
                "covrImgUrl": "",
                "fnb": 0,
                "mTkt": 1,
                "bCode": "0",
                "sTop": 0,
                "isMerchantCancellable": 0,
                "cinemaLogoUrl": "https://assetscdn1.paytm.com/images/cinema/Inox%20(1)-35ae9530-26fd-11ef-a342-13ea6c7d9d31.png",
                "cinemaVideoUrl": "",
                "appCoverVideoUrl": "",
                "webCoverVideoUrl": "",
                "amenities": null,
                "promos": null,
                "chainKey": "PVR",
                "contentId": 174518,
                "theatreGroupName": "",
                "amenitiesOrder": null,
                "carouselAttachments": [],
                "isPassEnabled": 1,
                "paytmCinemaId": 1024431,
                "city": "Jaipur",
                "clientId": "ticketnew",
                "isMapped": 0,
                "city_id": null,
                "is_city_mapped": null,
                "state": "rajasthan",
                "label": "PVR INOX Sunny Trade Center, Jaipur",
                "sessionCount": 89
            },
            {
                "id": 1024434,
                "pid": 1707,
                "name": "PVR INOX Mall of Jaipur",
                "address": "PVR Limited, 3rd Floor, Mall Of Jaipur, Gandhi Path W, B Block, Vaishali Nagar, Jaipur, Rajasthan 302021, India",
                "pincode": "302021",
                "lat": 26.9062,
                "lon": 75.7344,
                "cityId": 13,
                "appCovrImgUrl": "",
                "covrImgUrl": "",
                "fnb": 0,
                "mTkt": 1,
                "bCode": "0",
                "sTop": 0,
                "isMerchantCancellable": 0,
                "cinemaLogoUrl": "https://assetscdn1.paytm.com/images/cinema/PVR%20(1)-5604dfb0-e238-11ee-a3c7-f5f87f3f5d73.png",
                "cinemaVideoUrl": "",
                "appCoverVideoUrl": "",
                "webCoverVideoUrl": "",
                "amenities": null,
                "promos": null,
                "chainKey": "PVR",
                "contentId": 171312,
                "theatreGroupName": "",
                "amenitiesOrder": null,
                "carouselAttachments": [],
                "isPassEnabled": 1,
                "paytmCinemaId": 1024434,
                "city": "Jaipur",
                "clientId": "ticketnew",
                "isMapped": 0,
                "city_id": null,
                "is_city_mapped": null,
                "state": "rajasthan",
                "label": "PVR INOX Mall of Jaipur",
                "sessionCount": 151
            },
            {
                "id": 142,
                "pid": 335,
                "name": "Cinepolis Triton Mega Mall, Jhotwara Road",
                "address": "3rd Floor, Triton Mega Mall, Maharaja Shekhoje Roa Circle, Chomu Pulaia, Jhotwara Road, Jaipur, Rajasthan 302012, India",
                "pincode": "302012",
                "lat": 26.941139,
                "lon": 75.771363,
                "cityId": 13,
                "appCovrImgUrl": "",
                "covrImgUrl": "",
                "fnb": 0,
                "mTkt": 1,
                "bCode": "0750",
                "sTop": 0,
                "isMerchantCancellable": 0,
                "cinemaLogoUrl": "https://assetscdn1.paytm.com/images/cinema/Cinepolis-fe9077c0-b38f-11ee-9dc3-a7b6a49337da.png",
                "cinemaVideoUrl": "",
                "appCoverVideoUrl": "",
                "webCoverVideoUrl": "",
                "amenities": {
                    "1": 1,
                    "2": 1,
                    "3": -1,
                    "4": 1,
                    "5": -1,
                    "6": 1
                },
                "promos": null,
                "chainKey": "Cinepolis",
                "contentId": 147599,
                "theatreGroupName": "",
                "amenitiesOrder": [
                    {
                        "id": 1,
                        "rank": 2,
                        "status": 1
                    },
                    {
                        "id": 2,
                        "rank": 1,
                        "status": 1
                    },
                    {
                        "id": 3,
                        "rank": 3,
                        "status": -1
                    },
                    {
                        "id": 4,
                        "rank": 6,
                        "status": 1
                    },
                    {
                        "id": 5,
                        "rank": 4,
                        "status": -1
                    },
                    {
                        "id": 6,
                        "rank": 5,
                        "status": 1
                    }
                ],
                "carouselAttachments": [],
                "isPassEnabled": 0,
                "paytmCinemaId": 142,
                "city": "Jaipur",
                "clientId": "ticketnew",
                "isMapped": 0,
                "city_id": null,
                "is_city_mapped": null,
                "state": "rajasthan",
                "label": "Cinepolis Triton Mega Mall, Jhotwara Road",
                "sessionCount": 73
            }
        ],
        "filterData": {
            "minSTime": "03:10",
            "maxSTime": "16:35",
            "minPrice": 140.0,
            "maxPrice": 500.0,
            "premium": false,
            "freeSeats": false,
            "groupSeats": false,
            "tokenFeeSeats": false,
            "scnFrmts": [
                "2D"
            ],
            "sndFrmts": [
                "none"
            ],
            "mLangs": [
                "Telugu"
            ],
            "genres": [
                "Action",
                "Drama",
                "Thriller"
            ]
        }
    },
    "data": {
        "pageSize": 100,
        "cinemasOrder": [
            1024431,
            1024434,
            142
        ],
        "sessionDates": [
            "2024-09-27",
            "2024-09-28",
            "2024-09-29"
        ]
    },
    "pageData": {
        "sessions": {
            "1024431": [
                {
                    "sid": "53178",
                    "pid": 1707,
                    "pkey": "showbizz",
                    "cid": 1024431,
                    "mid": "OAV34I",
                    "fid": "TtdX_wUyN",
                    "showTime": "2024-09-27T08:35",
                    "closeTime": "2024-09-27T08:34",
                    "mandatoryItems": [],
                    "areas": [
                        {
                            "code": "CL",
                            "label": "Club",
                            "typeCode": "53178_CL",
                            "sType": "fixed",
                            "sAvail": 78,
                            "sTotal": 78,
                            "price": 200.0,
                            "statusColor": "G"
                        },
                        {
                            "code": "EX",
                            "label": "Executive",
                            "typeCode": "53178_EX",
                            "sType": "fixed",
                            "sAvail": 20,
                            "sTotal": 20,
                            "price": 180.0,
                            "statusColor": "G"
                        },
                        {
                            "code": "RR",
                            "label": "Royale Recliners",
                            "typeCode": "53178_RR",
                            "sType": "fixed",
                            "sAvail": 16,
                            "sTotal": 16,
                            "price": 310.0,
                            "statusColor": "G"
                        },
                        {
                            "code": "RY",
                            "label": "Royal",
                            "typeCode": "53178_RY",
                            "sType": "fixed",
                            "sAvail": 140,
                            "sTotal": 140,
                            "price": 220.0,
                            "statusColor": "G"
                        }
                    ],
                    "total": 254,
                    "avail": 254,
                    "audi": "SCREEN 4",
                    "premium": 0,
                    "tFeePkupTime": 0,
                    "sType": 0,
                    "tFee": 0,
                    "grpSeats": 0,
                    "maxTkt": 10,
                    "lang": "Telugu",
                    "scrnFmt": "2D",
                    "sndFmt": "none",
                    "gnrs": [
                        "Action",
                        "Drama",
                        "Thriller"
                    ],
                    "statusColor": "G"
                },
                {
                    "sid": "53123",
                    "pid": 1707,
                    "pkey": "showbizz",
                    "cid": 1024431,
                    "mid": "OAV34I",
                    "fid": "TtdX_wUyN",
                    "showTime": "2024-09-27T03:40",
                    "closeTime": "2024-09-27T03:39",
                    "mandatoryItems": [],
                    "areas": [
                        {
                            "code": "CL",
                            "label": "Club",
                            "typeCode": "53123_CL",
                            "sType": "fixed",
                            "sAvail": 35,
                            "sTotal": 60,
                            "price": 150.0,
                            "statusColor": "G"
                        },
                        {
                            "code": "EX",
                            "label": "Executive",
                            "typeCode": "53123_EX",
                            "sType": "fixed",
                            "sAvail": 15,
                            "sTotal": 15,
                            "price": 140.0,
                            "statusColor": "G"
                        },
                        {
                            "code": "RR",
                            "label": "Royale Recliners",
                            "typeCode": "53123_RR",
                            "sType": "fixed",
                            "sAvail": 5,
                            "sTotal": 11,
                            "price": 260.0,
                            "statusColor": "G"
                        },
                        {
                            "code": "RY",
                            "label": "Royal",
                            "typeCode": "53123_RY",
                            "sType": "fixed",
                            "sAvail": 41,
                            "sTotal": 103,
                            "price": 190.0,
                            "statusColor": "Y"
                        }
                    ],
                    "total": 189,
                    "avail": 96,
                    "audi": "SCREEN 2",
                    "premium": 0,
                    "tFeePkupTime": 0,
                    "sType": 0,
                    "tFee": 0,
                    "grpSeats": 0,
                    "maxTkt": 10,
                    "lang": "Telugu",
                    "scrnFmt": "2D",
                    "sndFmt": "none",
                    "gnrs": [
                        "Action",
                        "Drama",
                        "Thriller"
                    ],
                    "statusColor": "G"
                }
            ],
            "1024434": [
                {
                    "sid": "8603",
                    "pid": 1707,
                    "pkey": "showbizz",
                    "cid": 1024434,
                    "mid": "OAV34I",
                    "fid": "TtdX_wUyN",
                    "showTime": "2024-09-27T09:20",
                    "closeTime": "2024-09-27T09:19",
                    "mandatoryItems": [],
                    "areas": [
                        {
                            "code": "CL",
                            "label": "CLASSIC",
                            "typeCode": "8603_CL",
                            "sType": "fixed",
                            "sAvail": 26,
                            "sTotal": 26,
                            "price": 220.0,
                            "statusColor": "G"
                        },
                        {
                            "code": "PP",
                            "label": "PRIME PLUS",
                            "typeCode": "8603_PP",
                            "sType": "fixed",
                            "sAvail": 13,
                            "sTotal": 16,
                            "price": 260.0,
                            "statusColor": "G"
                        },
                        {
                            "code": "PR",
                            "label": "PRIME",
                            "typeCode": "8603_PR",
                            "sType": "fixed",
                            "sAvail": 103,
                            "sTotal": 103,
                            "price": 240.0,
                            "statusColor": "G"
                        },
                        {
                            "code": "RE",
                            "label": "RECLINER",
                            "typeCode": "8603_RE",
                            "sType": "fixed",
                            "sAvail": 12,
                            "sTotal": 12,
                            "price": 420.0,
                            "statusColor": "G"
                        }
                    ],
                    "total": 157,
                    "avail": 154,
                    "audi": "AUDI 05",
                    "premium": 0,
                    "tFeePkupTime": 0,
                    "sType": 0,
                    "tFee": 0,
                    "grpSeats": 0,
                    "maxTkt": 10,
                    "lang": "Telugu",
                    "scrnFmt": "2D",
                    "sndFmt": "none",
                    "gnrs": [
                        "Action",
                        "Drama",
                        "Thriller"
                    ],
                    "statusColor": "G"
                },
                {
                    "sid": "8604",
                    "pid": 1707,
                    "pkey": "showbizz",
                    "cid": 1024434,
                    "mid": "OAV34I",
                    "fid": "TtdX_wUyN",
                    "showTime": "2024-09-27T06:45",
                    "closeTime": "2024-09-27T06:44",
                    "mandatoryItems": [],
                    "areas": [
                        {
                            "code": "PR",
                            "label": "PRIME",
                            "typeCode": "8604_PR",
                            "sType": "fixed",
                            "sAvail": 107,
                            "sTotal": 107,
                            "price": 260.0,
                            "statusColor": "G"
                        },
                        {
                            "code": "RE",
                            "label": "RECLINER",
                            "typeCode": "8604_RE",
                            "sType": "fixed",
                            "sAvail": 9,
                            "sTotal": 12,
                            "price": 440.0,
                            "statusColor": "G"
                        },
                        {
                            "code": "CL",
                            "label": "CLASSIC",
                            "typeCode": "8604_CL",
                            "sType": "fixed",
                            "sAvail": 26,
                            "sTotal": 26,
                            "price": 240.0,
                            "statusColor": "G"
                        },
                        {
                            "code": "PP",
                            "label": "PRIME PLUS",
                            "typeCode": "8604_PP",
                            "sType": "fixed",
                            "sAvail": 17,
                            "sTotal": 17,
                            "price": 280.0,
                            "statusColor": "G"
                        }
                    ],
                    "total": 162,
                    "avail": 159,
                    "audi": "AUDI 04",
                    "premium": 0,
                    "tFeePkupTime": 0,
                    "sType": 0,
                    "tFee": 0,
                    "grpSeats": 0,
                    "maxTkt": 10,
                    "lang": "Telugu",
                    "scrnFmt": "2D",
                    "sndFmt": "none",
                    "gnrs": [
                        "Action",
                        "Drama",
                        "Thriller"
                    ],
                    "statusColor": "G"
                },
                {
                    "sid": "8592",
                    "pid": 1707,
                    "pkey": "showbizz",
                    "cid": 1024434,
                    "mid": "OAV34I",
                    "fid": "TtdX_wUyN",
                    "showTime": "2024-09-27T16:35",
                    "closeTime": "2024-09-27T16:34",
                    "mandatoryItems": [],
                    "areas": [
                        {
                            "code": "CL",
                            "label": "CLASSIC",
                            "typeCode": "8592_CL",
                            "sType": "fixed",
                            "sAvail": 20,
                            "sTotal": 20,
                            "price": 240.0,
                            "statusColor": "G"
                        },
                        {
                            "code": "PP",
                            "label": "PRIME PLUS",
                            "typeCode": "8592_PP",
                            "sType": "fixed",
                            "sAvail": 3,
                            "sTotal": 13,
                            "price": 320.0,
                            "statusColor": "Y"
                        },
                        {
                            "code": "PR",
                            "label": "PRIME",
                            "typeCode": "8592_PR",
                            "sType": "fixed",
                            "sAvail": 36,
                            "sTotal": 43,
                            "price": 260.0,
                            "statusColor": "G"
                        },
                        {
                            "code": "RE",
                            "label": "RECLINER",
                            "typeCode": "8592_RE",
                            "sType": "fixed",
                            "sAvail": 4,
                            "sTotal": 8,
                            "price": 500.0,
                            "statusColor": "G"
                        }
                    ],
                    "total": 84,
                    "avail": 63,
                    "audi": "AUDI 07",
                    "premium": 0,
                    "tFeePkupTime": 0,
                    "sType": 0,
                    "tFee": 0,
                    "grpSeats": 0,
                    "maxTkt": 10,
                    "lang": "Telugu",
                    "scrnFmt": "2D",
                    "sndFmt": "none",
                    "gnrs": [
                        "Action",
                        "Drama",
                        "Thriller"
                    ],
                    "statusColor": "G"
                },
                {
                    "sid": "8486",
                    "pid": 1707,
                    "pkey": "showbizz",
                    "cid": 1024434,
                    "mid": "OAV34I",
                    "fid": "TtdX_wUyN",
                    "showTime": "2024-09-27T03:10",
                    "closeTime": "2024-09-27T03:09",
                    "mandatoryItems": [],
                    "areas": [
                        {
                            "code": "CL",
                            "label": "CLASSIC",
                            "typeCode": "8486_CL",
                            "sType": "fixed",
                            "sAvail": 21,
                            "sTotal": 26,
                            "price": 180.0,
                            "statusColor": "G"
                        },
                        {
                            "code": "PP",
                            "label": "PRIME PLUS",
                            "typeCode": "8486_PP",
                            "sType": "fixed",
                            "sAvail": 0,
                            "sTotal": 17,
                            "price": 280.0,
                            "statusColor": "D"
                        },
                        {
                            "code": "PR",
                            "label": "PRIME",
                            "typeCode": "8486_PR",
                            "sType": "fixed",
                            "sAvail": 17,
                            "sTotal": 107,
                            "price": 260.0,
                            "statusColor": "Y"
                        },
                        {
                            "code": "RE",
                            "label": "RECLINER",
                            "typeCode": "8486_RE",
                            "sType": "fixed",
                            "sAvail": 0,
                            "sTotal": 12,
                            "price": 420.0,
                            "statusColor": "D"
                        }
                    ],
                    "total": 162,
                    "avail": 38,
                    "audi": "AUDI 04",
                    "premium": 0,
                    "tFeePkupTime": 0,
                    "sType": 0,
                    "tFee": 0,
                    "grpSeats": 0,
                    "maxTkt": 10,
                    "lang": "Telugu",
                    "scrnFmt": "2D",
                    "sndFmt": "none",
                    "gnrs": [
                        "Action",
                        "Drama",
                        "Thriller"
                    ],
                    "statusColor": "Y"
                },
                {
                    "sid": "8499",
                    "pid": 1707,
                    "pkey": "showbizz",
                    "cid": 1024434,
                    "mid": "OAV34I",
                    "fid": "TtdX_wUyN",
                    "showTime": "2024-09-27T12:55",
                    "closeTime": "2024-09-27T12:54",
                    "mandatoryItems": [],
                    "areas": [
                        {
                            "code": "CL",
                            "label": "CLASSIC",
                            "typeCode": "8499_CL",
                            "sType": "fixed",
                            "sAvail": 26,
                            "sTotal": 26,
                            "price": 240.0,
                            "statusColor": "G"
                        },
                        {
                            "code": "PP",
                            "label": "PRIME PLUS",
                            "typeCode": "8499_PP",
                            "sType": "fixed",
                            "sAvail": 0,
                            "sTotal": 16,
                            "price": 290.0,
                            "statusColor": "D"
                        },
                        {
                            "code": "PR",
                            "label": "PRIME",
                            "typeCode": "8499_PR",
                            "sType": "fixed",
                            "sAvail": 31,
                            "sTotal": 103,
                            "price": 320.0,
                            "statusColor": "Y"
                        },
                        {
                            "code": "RE",
                            "label": "RECLINER",
                            "typeCode": "8499_RE",
                            "sType": "fixed",
                            "sAvail": 0,
                            "sTotal": 12,
                            "price": 500.0,
                            "statusColor": "D"
                        }
                    ],
                    "total": 157,
                    "avail": 57,
                    "audi": "AUDI 05",
                    "premium": 0,
                    "tFeePkupTime": 0,
                    "sType": 0,
                    "tFee": 0,
                    "grpSeats": 0,
                    "maxTkt": 10,
                    "lang": "Telugu",
                    "scrnFmt": "2D",
                    "sndFmt": "none",
                    "gnrs": [
                        "Action",
                        "Drama",
                        "Thriller"
                    ],
                    "statusColor": "Y"
                }
            ],
            "142": [
                {
                    "sid": "67068",
                    "pid": 335,
                    "pkey": "vista_common_food",
                    "cid": 142,
                    "mid": "OAV34I",
                    "fid": "TtdX_wUyN",
                    "showTime": "2024-09-27T10:50",
                    "closeTime": "2024-09-27T10:49",
                    "mandatoryItems": [],
                    "areas": [
                        {
                            "code": "0000000000",
                            "label": "NORMAL",
                            "typeCode": "0002",
                            "sType": "fixed",
                            "sAvail": 72,
                            "sTotal": 72,
                            "price": 210.0,
                            "statusColor": "G"
                        },
                        {
                            "code": "0000000003",
                            "label": "VIP",
                            "typeCode": "0004",
                            "sType": "fixed",
                            "sAvail": 6,
                            "sTotal": 10,
                            "price": 400.0,
                            "statusColor": "G"
                        },
                        {
                            "code": "0000000002",
                            "label": "EXECUTIVE",
                            "typeCode": "0001",
                            "sType": "fixed",
                            "sAvail": 219,
                            "sTotal": 244,
                            "price": 230.0,
                            "statusColor": "G"
                        }
                    ],
                    "total": 326,
                    "avail": 297,
                    "audi": "AUDI 1",
                    "premium": 0,
                    "premiumLabel": "DOLBY 5.1",
                    "tFeePkupTime": 0,
                    "sType": 0,
                    "tFee": 0,
                    "grpSeats": 0,
                    "maxTkt": 10,
                    "lang": "Telugu",
                    "scrnFmt": "2D",
                    "sndFmt": "none",
                    "gnrs": [
                        "Action",
                        "Drama",
                        "Thriller"
                    ],
                    "statusColor": "G",
                    "subtitle": ""
                }
            ]
        }
    }
}