{
    "serverTime": 1727584291,
    "meta": {
        "movies": [
            {
                "id": "OAV34I",
                "frmtId": "TtdX_wUyN",
                "name": "Devara - Part 1",
                "imgPath": "https://assetscdn1.paytm.com/images/cinema/Devara---Part-1--705x750-ff23a0e0-ccc6-11ee-a6f3-b9b401515283.jpg",
                "appImgPath": "https://assetscdn1.paytm.com/images/cinema/Devara-608x800-87e29260-7834-11ef-ad27-dfa11df60ee4.jpg",
                "cvrPath": "https://assetscdn1.paytm.com/images/cinema/we-a407a150-7b23-11ef-84df-ff7d1a67840c.jpg",
                "appCvrPath": "https://assetscdn1.paytm.com/images/cinema/App-cover-a62c7d20-7b23-11ef-8892-f397183e5623.jpg",
                "thumbnail": null,
                "edgeBanner": "https://assetscdn1.paytm.com/images/cinema/Devara---Part-1--1035%E2%80%8A%C3%97%E2%80%8A420-118bd900-ccc7-11ee-a6f3-b9b401515283.jpg",
                "trailer": "https://youtu.be/5cx7rvMvAWo",
                "censor": "U/A",
                "duration": 178,
                "grn": [
                    "Action",
                    "Drama",
                    "Thriller"
                ],
                "scrnFmt": "2D",
                "sndFmt": "none",
                "rnr": {
                    "hasUReview": 1,
                    "hasContent": 1
                },
                "isNew": false,
                "imxImgUrl": null,
                "contentId": 159964,
                "label": "Devara - Part 1",
                "lang": "Telugu"
            }
        ],
        "filterBuckets": {
            "timeBuckets": [
                {
                    "sTime": "05:00",
                    "eTime": "11:59",
                    "desc": "5:00 AM to 11:59 AM",
                    "dText": "Morning",
                    "desc1": "Till 12 PM"
                },
                {
                    "sTime": "12:00",
                    "eTime": "15:59",
                    "desc": "12:00 PM to 3:59 PM",
                    "dText": "Afternoon",
                    "desc1": "Till 4 PM"
                },
                {
                    "sTime": "16:00",
                    "eTime": "18:59",
                    "desc": "4:00 PM to 6:59 PM",
                    "dText": "Evening",
                    "desc1": "Till 7 PM"
                },
                {
                    "sTime": "19:00",
                    "eTime": "04:59",
                    "desc": "7:00 PM to 4:59 AM",
                    "dText": "Night",
                    "desc1": "After 7 PM"
                }
            ],
            "priceBuckets": [
                {
                    "min": "0",
                    "max": "99",
                    "desc": "Below Rs 100"
                },
                {
                    "min": "100",
                    "max": "199",
                    "desc": "Rs 100 - Rs 199"
                },
                {
                    "min": "200",
                    "max": "299",
                    "desc": "Rs 200 - Rs 299"
                },
                {
                    "min": "300",
                    "max": "399",
                    "desc": "Rs 300 - Rs 399"
                },
                {
                    "min": "400",
                    "max": "NA",
                    "desc": "Rs 400 or above"
                }
            ],
            "showTimeBuckets": [
                {
                    "sTime": "00:00",
                    "eTime": "08:00",
                    "desc": "12 AM to 8 AM",
                    "dText": "Early Morning",
                    "desc1": "Till 8 AM"
                },
                {
                    "sTime": "08:00",
                    "eTime": "12:00",
                    "desc": "8 AM to 12 PM",
                    "dText": "Morning",
                    "desc1": "Till 12 PM"
                },
                {
                    "sTime": "12:00",
                    "eTime": "16:00",
                    "desc": "12 PM to 4 PM",
                    "dText": "Afternoon",
                    "desc1": "Till 4 PM"
                },
                {
                    "sTime": "16:00",
                    "eTime": "19:00",
                    "desc": "4 PM to 7 PM",
                    "dText": "Evening",
                    "desc1": "Till 7 PM"
                },
                {
                    "sTime": "19:00",
                    "eTime": "23:59",
                    "desc": "7 PM to 12 AM",
                    "dText": "Night",
                    "desc1": "Till 12 AM"
                }
            ]
        },
        "amenities": [
            {
                "id": 2,
                "name": "Parking",
                "rank": 1
            },
            {
                "id": 1,
                "name": "Mobile Ticket",
                "rank": 2
            },
            {
                "id": 3,
                "name": "Online Food",
                "rank": 3
            },
            {
                "id": 5,
                "name": "Recliners",
                "rank": 4
            },
            {
                "id": 6,
                "name": "Paytm Accepted",
                "rank": 5
            },
            {
                "id": 4,
                "name": "Wheelchair Friendly",
                "rank": 6
            },
            {
                "id": 7,
                "name": "RGB Laser",
                "rank": 7
            },
            {
                "id": 8,
                "name": "Dolby Atmos",
                "rank": 8
            },
            {
                "id": 9,
                "name": "IMAX",
                "rank": 9
            },
            {
                "id": 10,
                "name": "4K",
                "rank": 10
            },
            {
                "id": 11,
                "name": "AC",
                "rank": 11
            },
            {
                "id": 12,
                "name": "WIFI",
                "rank": 12
            },
            {
                "id": 13,
                "name": "Food Court",
                "rank": 13
            },
            {
                "id": 14,
                "name": "Gaming Zone",
                "rank": 14
            },
            {
                "id": 15,
                "name": "2K",
                "rank": 15
            },
            {
                "id": 16,
                "name": "4D",
                "rank": 16
            },
            {
                "id": 17,
                "name": "4DX",
                "rank": 17
            },
            {
                "id": 18,
                "name": "Dolby 7.1",
                "rank": 18
            },
            {
                "id": 19,
                "name": "Air conditioning",
                "rank": 19
            },
            {
                "id": 20,
                "name": "Metro Train",
                "rank": 20
            },
            {
                "id": 21,
                "name": "Sofa",
                "rank": 21
            },
            {
                "id": 22,
                "name": "Social Seating",
                "rank": 22
            },
            {
                "id": 23,
                "name": "Wheelchair Assistance",
                "rank": 23
            },
            {
                "id": 24,
                "name": "Silver Screen",
                "rank": 24
            },
            {
                "id": 25,
                "name": "Food & Beverages",
                "rank": 25
            },
            {
                "id": 26,
                "name": "Paper Less Ticketing",
                "rank": 26
            },
            {
                "id": 27,
                "name": "Handicapped Washroom",
                "rank": 27
            },
            {
                "id": 28,
                "name": "Free Parking",
                "rank": 28
            },
            {
                "id": 29,
                "name": "Baggage Counter",
                "rank": 29
            },
            {
                "id": 30,
                "name": "Dolby 4 Way 11.1",
                "rank": 30
            },
            {
                "id": 31,
                "name": "Barco 4K Ultra HD",
                "rank": 31
            }
        ],
        "cinemas": [
            {
                "id": 25808,
                "pid": 750,
                "name": "SVC Vijay Theatre, Nizamabad",
                "address": "Yellammagutta, Nizamabad, Telangana 503002, India",
                "pincode": "503002",
                "lat": 18.678619,
                "lon": 78.106966,
                "cityId": 220,
                "appCovrImgUrl": "",
                "covrImgUrl": "",
                "fnb": 0,
                "mTkt": 1,
                "bCode": "0",
                "sTop": 0,
                "isMerchantCancellable": 0,
                "cinemaLogoUrl": "https://assetscdn1.paytm.com/images/cinema/svc-5551d580-869c-11ed-9b16-5b1b1e9f8842.png",
                "cinemaVideoUrl": "",
                "appCoverVideoUrl": "",
                "webCoverVideoUrl": "",
                "amenities": null,
                "promos": null,
                "chainKey": "SVC Sangeetha",
                "contentId": 153413,
                "theatreGroupName": "",
                "amenitiesOrder": null,
                "carouselAttachments": [],
                "isPassEnabled": 0,
                "paytmCinemaId": 25808,
                "city": "Nizamabad",
                "clientId": "ticketnew",
                "isMapped": 0,
                "city_id": null,
                "is_city_mapped": null,
                "state": "telangana",
                "label": "SVC Vijay Theatre, Nizamabad",
                "sessionCount": 20
            },
            {
                "id": 1018795,
                "pid": 750,
                "name": "SVC Lalithamahal, Nizamabad",
                "address": "Namdevwada, Dubba Road, Gurbabadi Road, Near Railway Gate New Gunj, Nizamabad, Telangana 503002, India",
                "pincode": "503002",
                "lat": 18.67802,
                "lon": 78.09648,
                "cityId": 220,
                "appCovrImgUrl": "",
                "covrImgUrl": "",
                "fnb": 0,
                "mTkt": 0,
                "bCode": "",
                "sTop": 0,
                "isMerchantCancellable": 0,
                "cinemaLogoUrl": "https://assetscdn1.paytm.com/images/cinema/svc-5551d580-869c-11ed-9b16-5b1b1e9f8842%5B1%5D-729bd560-999b-11ee-931a-230dd0f33fac.png",
                "cinemaVideoUrl": "",
                "appCoverVideoUrl": "",
                "webCoverVideoUrl": "",
                "amenities": null,
                "promos": null,
                "chainKey": "SVC Sangeetha",
                "contentId": 168590,
                "theatreGroupName": "",
                "amenitiesOrder": null,
                "carouselAttachments": [],
                "isPassEnabled": 0,
                "paytmCinemaId": 1018795,
                "city": "Nizamabad",
                "clientId": "ticketnew",
                "isMapped": 0,
                "city_id": null,
                "is_city_mapped": null,
                "state": "telangana",
                "label": "SVC Lalithamahal, Nizamabad",
                "sessionCount": 20
            },
            {
                "id": 1024277,
                "pid": 1707,
                "name": "PVR INOX Venu Mall, Nizamabad",
                "address": "PVR Cinemas,  3th Floor, Venu Mall H. No. 5-6-661, Pragathi Nagar, Nizamabad, Telengana 503003, India",
                "pincode": "503003",
                "lat": 18.669163,
                "lon": 78.10527,
                "cityId": 220,
                "appCovrImgUrl": "",
                "covrImgUrl": "",
                "fnb": 0,
                "mTkt": 1,
                "bCode": "",
                "sTop": 0,
                "isMerchantCancellable": 0,
                "cinemaLogoUrl": "https://assetscdn1.paytm.com/images/cinema/PVR%20(1)-e21ffbe0-e04b-11ee-b37f-29404991a0ba.png",
                "cinemaVideoUrl": "",
                "appCoverVideoUrl": "",
                "webCoverVideoUrl": "",
                "amenities": null,
                "promos": null,
                "chainKey": "PVR",
                "contentId": 171173,
                "theatreGroupName": "",
                "amenitiesOrder": null,
                "carouselAttachments": [],
                "isPassEnabled": 1,
                "paytmCinemaId": 1024277,
                "city": "Nizamabad",
                "clientId": "ticketnew",
                "isMapped": 0,
                "city_id": null,
                "is_city_mapped": null,
                "state": "telangana",
                "label": "PVR INOX Venu Mall, Nizamabad",
                "sessionCount": 28
            }
        ],
        "filterData": {
            "minSTime": "05:15",
            "maxSTime": "17:20",
            "minPrice": 80.0,
            "maxPrice": 413.0,
            "premium": false,
            "freeSeats": false,
            "groupSeats": false,
            "tokenFeeSeats": false,
            "scnFrmts": [
                "2D"
            ],
            "sndFrmts": [
                "none"
            ],
            "mLangs": [
                "Telugu"
            ],
            "genres": [
                "Action",
                "Drama",
                "Thriller"
            ]
        }
    },
    "data": {
        "pageSize": 100,
        "cinemasOrder": [
            25808,
            1018795,
            1024277
        ],
        "sessionDates": [
            "2024-09-29",
            "2024-09-30",
            "2024-10-01",
            "2024-10-02",
            "2024-10-03"
        ]
    },
    "pageData": {
        "sessions": {
            "25808": [
                {
                    "sid": "30556__1727613000__4329__5207",
                    "pid": 750,
                    "pkey": "ticketnew",
                    "cid": 25808,
                    "mid": "OAV34I",
                    "fid": "TtdX_wUyN",
                    "showTime": "2024-09-29T12:30",
                    "closeTime": "2024-09-29T12:15",
                    "mandatoryItems": [],
                    "areas": [
                        {
                            "code": "1",
                            "label": "PLATINUM",
                            "typeCode": "30556__1727613000__4329__5207_PLATINUM",
                            "sType": "fixed",
                            "sAvail": 367,
                            "sTotal": 476,
                            "price": 205.0,
                            "statusColor": "G"
                        },
                        {
                            "code": "2",
                            "label": "GOLD",
                            "typeCode": "30556__1727613000__4329__5207_GOLD",
                            "sType": "fixed",
                            "sAvail": 0,
                            "sTotal": 20,
                            "price": 145.0,
                            "statusColor": "D"
                        },
                        {
                            "code": "3",
                            "label": "SILVER",
                            "typeCode": "30556__1727613000__4329__5207_SILVER",
                            "sType": "fixed",
                            "sAvail": 89,
                            "sTotal": 125,
                            "price": 80.0,
                            "statusColor": "G"
                        }
                    ],
                    "total": 621,
                    "avail": 456,
                    "audi": "SVC Vijay Theatre",
                    "premium": 0,
                    "tFeePkupTime": 0,
                    "sType": 0,
                    "tFee": 0,
                    "grpSeats": 0,
                    "maxTkt": 6,
                    "lang": "Telugu",
                    "scrnFmt": "2D",
                    "sndFmt": "none",
                    "gnrs": [
                        "Action",
                        "Drama",
                        "Thriller"
                    ],
                    "statusColor": "G",
                    "subtitle": ""
                },
                {
                    "sid": "30556__1727587200__4329__5205",
                    "pid": 750,
                    "pkey": "ticketnew",
                    "cid": 25808,
                    "mid": "OAV34I",
                    "fid": "TtdX_wUyN",
                    "showTime": "2024-09-29T05:20",
                    "closeTime": "2024-09-29T05:05",
                    "mandatoryItems": [],
                    "areas": [
                        {
                            "code": "1",
                            "label": "PLATINUM",
                            "typeCode": "30556__1727587200__4329__5205_PLATINUM",
                            "sType": "fixed",
                            "sAvail": 396,
                            "sTotal": 476,
                            "price": 205.0,
                            "statusColor": "G"
                        },
                        {
                            "code": "2",
                            "label": "GOLD",
                            "typeCode": "30556__1727587200__4329__5205_GOLD",
                            "sType": "fixed",
                            "sAvail": 0,
                            "sTotal": 20,
                            "price": 145.0,
                            "statusColor": "D"
                        },
                        {
                            "code": "3",
                            "label": "SILVER",
                            "typeCode": "30556__1727587200__4329__5205_SILVER",
                            "sType": "fixed",
                            "sAvail": 89,
                            "sTotal": 125,
                            "price": 80.0,
                            "statusColor": "G"
                        }
                    ],
                    "total": 621,
                    "avail": 485,
                    "audi": "SVC Vijay Theatre",
                    "premium": 0,
                    "tFeePkupTime": 0,
                    "sType": 0,
                    "tFee": 0,
                    "grpSeats": 0,
                    "maxTkt": 6,
                    "lang": "Telugu",
                    "scrnFmt": "2D",
                    "sndFmt": "none",
                    "gnrs": [
                        "Action",
                        "Drama",
                        "Thriller"
                    ],
                    "statusColor": "G",
                    "subtitle": ""
                },
                {
                    "sid": "30556__1727599500__4329__5206",
                    "pid": 750,
                    "pkey": "ticketnew",
                    "cid": 25808,
                    "mid": "OAV34I",
                    "fid": "TtdX_wUyN",
                    "showTime": "2024-09-29T08:45",
                    "closeTime": "2024-09-29T08:30",
                    "mandatoryItems": [],
                    "areas": [
                        {
                            "code": "1",
                            "label": "PLATINUM",
                            "typeCode": "30556__1727599500__4329__5206_PLATINUM",
                            "sType": "fixed",
                            "sAvail": 325,
                            "sTotal": 476,
                            "price": 205.0,
                            "statusColor": "G"
                        },
                        {
                            "code": "2",
                            "label": "GOLD",
                            "typeCode": "30556__1727599500__4329__5206_GOLD",
                            "sType": "fixed",
                            "sAvail": 0,
                            "sTotal": 20,
                            "price": 145.0,
                            "statusColor": "D"
                        },
                        {
                            "code": "3",
                            "label": "SILVER",
                            "typeCode": "30556__1727599500__4329__5206_SILVER",
                            "sType": "fixed",
                            "sAvail": 93,
                            "sTotal": 125,
                            "price": 80.0,
                            "statusColor": "G"
                        }
                    ],
                    "total": 621,
                    "avail": 418,
                    "audi": "SVC Vijay Theatre",
                    "premium": 0,
                    "tFeePkupTime": 0,
                    "sType": 0,
                    "tFee": 0,
                    "grpSeats": 0,
                    "maxTkt": 6,
                    "lang": "Telugu",
                    "scrnFmt": "2D",
                    "sndFmt": "none",
                    "gnrs": [
                        "Action",
                        "Drama",
                        "Thriller"
                    ],
                    "statusColor": "G",
                    "subtitle": ""
                },
                {
                    "sid": "30556__1727625600__4329__5208",
                    "pid": 750,
                    "pkey": "ticketnew",
                    "cid": 25808,
                    "mid": "OAV34I",
                    "fid": "TtdX_wUyN",
                    "showTime": "2024-09-29T16:00",
                    "closeTime": "2024-09-29T15:45",
                    "mandatoryItems": [],
                    "areas": [
                        {
                            "code": "1",
                            "label": "PLATINUM",
                            "typeCode": "30556__1727625600__4329__5208_PLATINUM",
                            "sType": "fixed",
                            "sAvail": 441,
                            "sTotal": 476,
                            "price": 205.0,
                            "statusColor": "G"
                        },
                        {
                            "code": "2",
                            "label": "GOLD",
                            "typeCode": "30556__1727625600__4329__5208_GOLD",
                            "sType": "fixed",
                            "sAvail": 0,
                            "sTotal": 20,
                            "price": 145.0,
                            "statusColor": "D"
                        },
                        {
                            "code": "3",
                            "label": "SILVER",
                            "typeCode": "30556__1727625600__4329__5208_SILVER",
                            "sType": "fixed",
                            "sAvail": 101,
                            "sTotal": 125,
                            "price": 80.0,
                            "statusColor": "G"
                        }
                    ],
                    "total": 621,
                    "avail": 542,
                    "audi": "SVC Vijay Theatre",
                    "premium": 0,
                    "tFeePkupTime": 0,
                    "sType": 0,
                    "tFee": 0,
                    "grpSeats": 0,
                    "maxTkt": 6,
                    "lang": "Telugu",
                    "scrnFmt": "2D",
                    "sndFmt": "none",
                    "gnrs": [
                        "Action",
                        "Drama",
                        "Thriller"
                    ],
                    "statusColor": "G",
                    "subtitle": ""
                }
            ],
            "1018795": [
                {
                    "sid": "30556__1727599500__4194__6273",
                    "pid": 750,
                    "pkey": "ticketnew",
                    "cid": 1018795,
                    "mid": "OAV34I",
                    "fid": "TtdX_wUyN",
                    "showTime": "2024-09-29T08:45",
                    "closeTime": "2024-09-29T08:35",
                    "mandatoryItems": [],
                    "areas": [
                        {
                            "code": "10",
                            "label": "A BALCONY",
                            "typeCode": "30556__1727599500__4194__6273_A BALCONY",
                            "sType": "fixed",
                            "sAvail": 237,
                            "sTotal": 276,
                            "price": 205.0,
                            "statusColor": "G"
                        },
                        {
                            "code": "20",
                            "label": "B BALCONY",
                            "typeCode": "30556__1727599500__4194__6273_B BALCONY",
                            "sType": "fixed",
                            "sAvail": 264,
                            "sTotal": 264,
                            "price": 205.0,
                            "statusColor": "G"
                        },
                        {
                            "code": "30",
                            "label": "DELUXE CERCILE",
                            "typeCode": "30556__1727599500__4194__6273_DELUXE CERCILE",
                            "sType": "fixed",
                            "sAvail": 140,
                            "sTotal": 140,
                            "price": 145.0,
                            "statusColor": "G"
                        },
                        {
                            "code": "40",
                            "label": "FIRST CLASS",
                            "typeCode": "30556__1727599500__4194__6273_FIRST CLASS",
                            "sType": "fixed",
                            "sAvail": 166,
                            "sTotal": 170,
                            "price": 80.0,
                            "statusColor": "G"
                        }
                    ],
                    "total": 850,
                    "avail": 807,
                    "audi": "SVC Lalitha Mahal",
                    "premium": 0,
                    "tFeePkupTime": 0,
                    "sType": 0,
                    "tFee": 0,
                    "grpSeats": 0,
                    "maxTkt": 6,
                    "lang": "Telugu",
                    "scrnFmt": "2D",
                    "sndFmt": "none",
                    "gnrs": [
                        "Action",
                        "Drama",
                        "Thriller"
                    ],
                    "statusColor": "G",
                    "subtitle": ""
                },
                {
                    "sid": "30556__1727625600__4194__6275",
                    "pid": 750,
                    "pkey": "ticketnew",
                    "cid": 1018795,
                    "mid": "OAV34I",
                    "fid": "TtdX_wUyN",
                    "showTime": "2024-09-29T16:00",
                    "closeTime": "2024-09-29T15:50",
                    "mandatoryItems": [],
                    "areas": [
                        {
                            "code": "10",
                            "label": "A BALCONY",
                            "typeCode": "30556__1727625600__4194__6275_A BALCONY",
                            "sType": "fixed",
                            "sAvail": 268,
                            "sTotal": 276,
                            "price": 205.0,
                            "statusColor": "G"
                        },
                        {
                            "code": "20",
                            "label": "B BALCONY",
                            "typeCode": "30556__1727625600__4194__6275_B BALCONY",
                            "sType": "fixed",
                            "sAvail": 264,
                            "sTotal": 264,
                            "price": 205.0,
                            "statusColor": "G"
                        },
                        {
                            "code": "30",
                            "label": "DELUXE CERCILE",
                            "typeCode": "30556__1727625600__4194__6275_DELUXE CERCILE",
                            "sType": "fixed",
                            "sAvail": 140,
                            "sTotal": 140,
                            "price": 145.0,
                            "statusColor": "G"
                        },
                        {
                            "code": "40",
                            "label": "FIRST CLASS",
                            "typeCode": "30556__1727625600__4194__6275_FIRST CLASS",
                            "sType": "fixed",
                            "sAvail": 166,
                            "sTotal": 170,
                            "price": 80.0,
                            "statusColor": "G"
                        }
                    ],
                    "total": 850,
                    "avail": 838,
                    "audi": "SVC Lalitha Mahal",
                    "premium": 0,
                    "tFeePkupTime": 0,
                    "sType": 0,
                    "tFee": 0,
                    "grpSeats": 0,
                    "maxTkt": 6,
                    "lang": "Telugu",
                    "scrnFmt": "2D",
                    "sndFmt": "none",
                    "gnrs": [
                        "Action",
                        "Drama",
                        "Thriller"
                    ],
                    "statusColor": "G",
                    "subtitle": ""
                },
                {
                    "sid": "30556__1727586900__4194__6272",
                    "pid": 750,
                    "pkey": "ticketnew",
                    "cid": 1018795,
                    "mid": "OAV34I",
                    "fid": "TtdX_wUyN",
                    "showTime": "2024-09-29T05:15",
                    "closeTime": "2024-09-29T05:05",
                    "mandatoryItems": [],
                    "areas": [
                        {
                            "code": "10",
                            "label": "A BALCONY",
                            "typeCode": "30556__1727586900__4194__6272_A BALCONY",
                            "sType": "fixed",
                            "sAvail": 258,
                            "sTotal": 276,
                            "price": 205.0,
                            "statusColor": "G"
                        },
                        {
                            "code": "20",
                            "label": "B BALCONY",
                            "typeCode": "30556__1727586900__4194__6272_B BALCONY",
                            "sType": "fixed",
                            "sAvail": 264,
                            "sTotal": 264,
                            "price": 205.0,
                            "statusColor": "G"
                        },
                        {
                            "code": "30",
                            "label": "DELUXE CERCILE",
                            "typeCode": "30556__1727586900__4194__6272_DELUXE CERCILE",
                            "sType": "fixed",
                            "sAvail": 132,
                            "sTotal": 140,
                            "price": 145.0,
                            "statusColor": "G"
                        },
                        {
                            "code": "40",
                            "label": "FIRST CLASS",
                            "typeCode": "30556__1727586900__4194__6272_FIRST CLASS",
                            "sType": "fixed",
                            "sAvail": 163,
                            "sTotal": 170,
                            "price": 80.0,
                            "statusColor": "G"
                        }
                    ],
                    "total": 850,
                    "avail": 817,
                    "audi": "SVC Lalitha Mahal",
                    "premium": 0,
                    "tFeePkupTime": 0,
                    "sType": 0,
                    "tFee": 0,
                    "grpSeats": 0,
                    "maxTkt": 6,
                    "lang": "Telugu",
                    "scrnFmt": "2D",
                    "sndFmt": "none",
                    "gnrs": [
                        "Action",
                        "Drama",
                        "Thriller"
                    ],
                    "statusColor": "G",
                    "subtitle": ""
                },
                {
                    "sid": "30556__1727613000__4194__6274",
                    "pid": 750,
                    "pkey": "ticketnew",
                    "cid": 1018795,
                    "mid": "OAV34I",
                    "fid": "TtdX_wUyN",
                    "showTime": "2024-09-29T12:30",
                    "closeTime": "2024-09-29T12:20",
                    "mandatoryItems": [],
                    "areas": [
                        {
                            "code": "10",
                            "label": "A BALCONY",
                            "typeCode": "30556__1727613000__4194__6274_A BALCONY",
                            "sType": "fixed",
                            "sAvail": 232,
                            "sTotal": 276,
                            "price": 205.0,
                            "statusColor": "G"
                        },
                        {
                            "code": "20",
                            "label": "B BALCONY",
                            "typeCode": "30556__1727613000__4194__6274_B BALCONY",
                            "sType": "fixed",
                            "sAvail": 264,
                            "sTotal": 264,
                            "price": 205.0,
                            "statusColor": "G"
                        },
                        {
                            "code": "30",
                            "label": "DELUXE CERCILE",
                            "typeCode": "30556__1727613000__4194__6274_DELUXE CERCILE",
                            "sType": "fixed",
                            "sAvail": 134,
                            "sTotal": 140,
                            "price": 145.0,
                            "statusColor": "G"
                        },
                        {
                            "code": "40",
                            "label": "FIRST CLASS",
                            "typeCode": "30556__1727613000__4194__6274_FIRST CLASS",
                            "sType": "fixed",
                            "sAvail": 167,
                            "sTotal": 170,
                            "price": 80.0,
                            "statusColor": "G"
                        }
                    ],
                    "total": 850,
                    "avail": 797,
                    "audi": "SVC Lalitha Mahal",
                    "premium": 0,
                    "tFeePkupTime": 0,
                    "sType": 0,
                    "tFee": 0,
                    "grpSeats": 0,
                    "maxTkt": 6,
                    "lang": "Telugu",
                    "scrnFmt": "2D",
                    "sndFmt": "none",
                    "gnrs": [
                        "Action",
                        "Drama",
                        "Thriller"
                    ],
                    "statusColor": "G",
                    "subtitle": ""
                }
            ],
            "1024277": [
                {
                    "sid": "4288",
                    "pid": 1707,
                    "pkey": "showbizz",
                    "cid": 1024277,
                    "mid": "OAV34I",
                    "fid": "TtdX_wUyN",
                    "showTime": "2024-09-29T05:45",
                    "closeTime": "2024-09-29T05:44",
                    "mandatoryItems": [],
                    "areas": [
                        {
                            "code": "CL",
                            "label": "CLASSIC",
                            "typeCode": "4288_CL",
                            "sType": "fixed",
                            "sAvail": 222,
                            "sTotal": 329,
                            "price": 354.0,
                            "statusColor": "G"
                        },
                        {
                            "code": "RE",
                            "label": "RECLINER",
                            "typeCode": "4288_RE",
                            "sType": "fixed",
                            "sAvail": 3,
                            "sTotal": 16,
                            "price": 413.0,
                            "statusColor": "Y"
                        }
                    ],
                    "total": 345,
                    "avail": 225,
                    "audi": "AUDI 01",
                    "premium": 0,
                    "tFeePkupTime": 0,
                    "sType": 0,
                    "tFee": 0,
                    "grpSeats": 0,
                    "maxTkt": 6,
                    "lang": "Telugu",
                    "scrnFmt": "2D",
                    "sndFmt": "none",
                    "gnrs": [
                        "Action",
                        "Drama",
                        "Thriller"
                    ],
                    "statusColor": "G"
                },
                {
                    "sid": "4289",
                    "pid": 1707,
                    "pkey": "showbizz",
                    "cid": 1024277,
                    "mid": "OAV34I",
                    "fid": "TtdX_wUyN",
                    "showTime": "2024-09-29T09:20",
                    "closeTime": "2024-09-29T09:19",
                    "mandatoryItems": [],
                    "areas": [
                        {
                            "code": "CL",
                            "label": "CLASSIC",
                            "typeCode": "4289_CL",
                            "sType": "fixed",
                            "sAvail": 237,
                            "sTotal": 329,
                            "price": 354.0,
                            "statusColor": "G"
                        },
                        {
                            "code": "RE",
                            "label": "RECLINER",
                            "typeCode": "4289_RE",
                            "sType": "fixed",
                            "sAvail": 0,
                            "sTotal": 16,
                            "price": 413.0,
                            "statusColor": "D"
                        }
                    ],
                    "total": 345,
                    "avail": 237,
                    "audi": "AUDI 01",
                    "premium": 0,
                    "tFeePkupTime": 0,
                    "sType": 0,
                    "tFee": 0,
                    "grpSeats": 0,
                    "maxTkt": 6,
                    "lang": "Telugu",
                    "scrnFmt": "2D",
                    "sndFmt": "none",
                    "gnrs": [
                        "Action",
                        "Drama",
                        "Thriller"
                    ],
                    "statusColor": "G"
                },
                {
                    "sid": "4303",
                    "pid": 1707,
                    "pkey": "showbizz",
                    "cid": 1024277,
                    "mid": "OAV34I",
                    "fid": "TtdX_wUyN",
                    "showTime": "2024-09-29T13:40",
                    "closeTime": "2024-09-29T13:39",
                    "mandatoryItems": [],
                    "areas": [
                        {
                            "code": "CL",
                            "label": "CLASSIC",
                            "typeCode": "4303_CL",
                            "sType": "fixed",
                            "sAvail": 319,
                            "sTotal": 336,
                            "price": 354.0,
                            "statusColor": "G"
                        },
                        {
                            "code": "RE",
                            "label": "RECLINER",
                            "typeCode": "4303_RE",
                            "sType": "fixed",
                            "sAvail": 1,
                            "sTotal": 13,
                            "price": 413.0,
                            "statusColor": "R"
                        }
                    ],
                    "total": 349,
                    "avail": 320,
                    "audi": "AUDI 02",
                    "premium": 0,
                    "tFeePkupTime": 0,
                    "sType": 0,
                    "tFee": 0,
                    "grpSeats": 0,
                    "maxTkt": 6,
                    "lang": "Telugu",
                    "scrnFmt": "2D",
                    "sndFmt": "none",
                    "gnrs": [
                        "Action",
                        "Drama",
                        "Thriller"
                    ],
                    "statusColor": "G"
                },
                {
                    "sid": "4304",
                    "pid": 1707,
                    "pkey": "showbizz",
                    "cid": 1024277,
                    "mid": "OAV34I",
                    "fid": "TtdX_wUyN",
                    "showTime": "2024-09-29T17:20",
                    "closeTime": "2024-09-29T17:19",
                    "mandatoryItems": [],
                    "areas": [
                        {
                            "code": "CL",
                            "label": "CLASSIC",
                            "typeCode": "4304_CL",
                            "sType": "fixed",
                            "sAvail": 334,
                            "sTotal": 336,
                            "price": 354.0,
                            "statusColor": "G"
                        },
                        {
                            "code": "RE",
                            "label": "RECLINER",
                            "typeCode": "4304_RE",
                            "sType": "fixed",
                            "sAvail": 11,
                            "sTotal": 13,
                            "price": 413.0,
                            "statusColor": "G"
                        }
                    ],
                    "total": 349,
                    "avail": 345,
                    "audi": "AUDI 02",
                    "premium": 0,
                    "tFeePkupTime": 0,
                    "sType": 0,
                    "tFee": 0,
                    "grpSeats": 0,
                    "maxTkt": 6,
                    "lang": "Telugu",
                    "scrnFmt": "2D",
                    "sndFmt": "none",
                    "gnrs": [
                        "Action",
                        "Drama",
                        "Thriller"
                    ],
                    "statusColor": "G"
                },
                {
                    "sid": "4291",
                    "pid": 1707,
                    "pkey": "showbizz",
                    "cid": 1024277,
                    "mid": "OAV34I",
                    "fid": "TtdX_wUyN",
                    "showTime": "2024-09-29T16:30",
                    "closeTime": "2024-09-29T16:29",
                    "mandatoryItems": [],
                    "areas": [
                        {
                            "code": "CL",
                            "label": "CLASSIC",
                            "typeCode": "4291_CL",
                            "sType": "fixed",
                            "sAvail": 325,
                            "sTotal": 329,
                            "price": 354.0,
                            "statusColor": "G"
                        },
                        {
                            "code": "RE",
                            "label": "RECLINER",
                            "typeCode": "4291_RE",
                            "sType": "fixed",
                            "sAvail": 0,
                            "sTotal": 16,
                            "price": 413.0,
                            "statusColor": "D"
                        }
                    ],
                    "total": 345,
                    "avail": 325,
                    "audi": "AUDI 01",
                    "premium": 0,
                    "tFeePkupTime": 0,
                    "sType": 0,
                    "tFee": 0,
                    "grpSeats": 0,
                    "maxTkt": 6,
                    "lang": "Telugu",
                    "scrnFmt": "2D",
                    "sndFmt": "none",
                    "gnrs": [
                        "Action",
                        "Drama",
                        "Thriller"
                    ],
                    "statusColor": "G"
                },
                {
                    "sid": "4290",
                    "pid": 1707,
                    "pkey": "showbizz",
                    "cid": 1024277,
                    "mid": "OAV34I",
                    "fid": "TtdX_wUyN",
                    "showTime": "2024-09-29T12:55",
                    "closeTime": "2024-09-29T12:54",
                    "mandatoryItems": [],
                    "areas": [
                        {
                            "code": "CL",
                            "label": "CLASSIC",
                            "typeCode": "4290_CL",
                            "sType": "fixed",
                            "sAvail": 282,
                            "sTotal": 329,
                            "price": 354.0,
                            "statusColor": "G"
                        },
                        {
                            "code": "RE",
                            "label": "RECLINER",
                            "typeCode": "4290_RE",
                            "sType": "fixed",
                            "sAvail": 2,
                            "sTotal": 16,
                            "price": 413.0,
                            "statusColor": "Y"
                        }
                    ],
                    "total": 345,
                    "avail": 284,
                    "audi": "AUDI 01",
                    "premium": 0,
                    "tFeePkupTime": 0,
                    "sType": 0,
                    "tFee": 0,
                    "grpSeats": 0,
                    "maxTkt": 6,
                    "lang": "Telugu",
                    "scrnFmt": "2D",
                    "sndFmt": "none",
                    "gnrs": [
                        "Action",
                        "Drama",
                        "Thriller"
                    ],
                    "statusColor": "G"
                }
            ]
        }
    }
}